hpml/__init__.py
hpml/centerer.py
hpml/hpml_compiler.py
hpml/lookups.py
hpml/preprocessor.py
hpml/utils.py
hpml/data/hpml.lang
hpml/data/packages.tex
hpml/data/semantics.json
hpml/data/syntactics.json
hpml-1.9.0.dist-info/METADATA
hpml-1.9.0.dist-info/WHEEL
hpml-1.9.0.dist-info/top_level.txt
hpml-1.9.0.dist-info/RECORD
