Metadata-Version: 2.1
Name: hpml
Version: 1.9.0
Summary: Hosker's Poetical Markup Language
Home-page: https://github.com/tomhosker/hpml
Author: Tom Hosker
Author-email: tomdothosker@gmail.com
License: MIT
Requires-Dist: hosker-utils
